[
  {
    "record_type_id": "YS",
    "data_division": "3",
    "data_created_date": "2025-01-07",
    "event_year": "2025",
    "event_date": "01-05",
    "racecourse_code": "06",
    "event_round": "01",
    "event_day": "01",
    "weekday_code": "2"
  },
  {
    "record_type_id": "YS",
    "data_division": "3",
    "data_created_date": "2025-01-07",
    "event_year": "2025",
    "event_date": "01-05",
    "racecourse_code": "07",
    "event_round": "01",
    "event_day": "01",
    "weekday_code": "2"
  },
  {
    "record_type_id": "YS",
    "data_division": "3",
    "data_created_date": "2025-01-07",
    "event_year": "2025",
    "event_date": "01-06",
    "racecourse_code": "06",
    "event_round": "01",
    "event_day": "02",
    "weekday_code": "4"
  },
  {
    "record_type_id": "YS",
    "data_division": "3",
    "data_created_date": "2025-01-07",
    "event_year": "2025",
    "event_date": "01-06",
    "racecourse_code": "07",
    "event_round": "01",
    "event_day": "02",
    "weekday_code": "4"
  },
  {
    "record_type_id": "YS",
    "data_division": "3",
    "data_created_date": "2025-01-14",
    "event_year": "2025",
    "event_date": "01-11",
    "racecourse_code": "06",
    "event_round": "01",
    "event_day": "03",
    "weekday_code": "1"
  },
  {
    "record_type_id": "YS",
    "data_division": "3",
    "data_created_date": "2025-01-14",
    "event_year": "2025",
    "event_date": "01-11",
    "racecourse_code": "07",
    "event_round": "01",
    "event_day": "03",
    "weekday_code": "1"
  },
  {
    "record_type_id": "YS",
    "data_division": "3",
    "data_created_date": "2025-01-14",
    "event_year": "2025",
    "event_date": "01-12",
    "racecourse_code": "06",
    "event_round": "01",
    "event_day": "04",
    "weekday_code": "2"
  },
  {
    "record_type_id": "YS",
    "data_division": "3",
    "data_created_date": "2025-01-14",
    "event_year": "2025",
    "event_date": "01-12",
    "racecourse_code": "07",
    "event_round": "01",
    "event_day": "04",
    "weekday_code": "2"
  },
  {
    "record_type_id": "YS",
    "data_division": "3",
    "data_created_date": "2025-01-14",
    "event_year": "2025",
    "event_date": "01-13",
    "racecourse_code": "06",
    "event_round": "01",
    "event_day": "05",
    "weekday_code": "3"
  },
  {
    "record_type_id": "YS",
    "data_division": "3",
    "data_created_date": "2025-01-14",
    "event_year": "2025",
    "event_date": "01-13",
    "racecourse_code": "07",
    "event_round": "01",
    "event_day": "05",
    "weekday_code": "3"
  },
  {
    "record_type_id": "YS",
    "data_division": "3",
    "data_created_date": "2025-01-20",
    "event_year": "2025",
    "event_date": "01-18",
    "racecourse_code": "06",
    "event_round": "01",
    "event_day": "06",
    "weekday_code": "1"
  },
  {
    "record_type_id": "YS",
    "data_division": "3",
    "data_created_date": "2025-01-20",
    "event_year": "2025",
    "event_date": "01-18",
    "racecourse_code": "07",
    "event_round": "01",
    "event_day": "06",
    "weekday_code": "1"
  },
  {
    "record_type_id": "YS",
    "data_division": "3",
    "data_created_date": "2025-01-20",
    "event_year": "2025",
    "event_date": "01-19",
    "racecourse_code": "06",
    "event_round": "01",
    "event_day": "07",
    "weekday_code": "2"
  },
  {
    "record_type_id": "YS",
    "data_division": "3",
    "data_created_date": "2025-01-20",
    "event_year": "2025",
    "event_date": "01-19",
    "racecourse_code": "07",
    "event_round": "01",
    "event_day": "07",
    "weekday_code": "2"
  },
  {
    "record_type_id": "YS",
    "data_division": "3",
    "data_created_date": "2025-01-27",
    "event_year": "2025",
    "event_date": "01-25",
    "racecourse_code": "06",
    "event_round": "01",
    "event_day": "08",
    "weekday_code": "1"
  },
  {
    "record_type_id": "YS",
    "data_division": "3",
    "data_created_date": "2025-01-27",
    "event_year": "2025",
    "event_date": "01-25",
    "racecourse_code": "07",
    "event_round": "01",
    "event_day": "08",
    "weekday_code": "1"
  },
  {
    "record_type_id": "YS",
    "data_division": "3",
    "data_created_date": "2025-01-27",
    "event_year": "2025",
    "event_date": "01-25",
    "racecourse_code": "10",
    "event_round": "01",
    "event_day": "01",
    "weekday_code": "1"
  },
  {
    "record_type_id": "YS",
    "data_division": "3",
    "data_created_date": "2025-01-27",
    "event_year": "2025",
    "event_date": "01-26",
    "racecourse_code": "06",
    "event_round": "01",
    "event_day": "09",
    "weekday_code": "2"
  },
  {
    "record_type_id": "YS",
    "data_division": "3",
    "data_created_date": "2025-01-27",
    "event_year": "2025",
    "event_date": "01-26",
    "racecourse_code": "07",
    "event_round": "01",
    "event_day": "09",
    "weekday_code": "2"
  },
  {
    "record_type_id": "YS",
    "data_division": "3",
    "data_created_date": "2025-01-27",
    "event_year": "2025",
    "event_date": "01-26",
    "racecourse_code": "10",
    "event_round": "01",
    "event_day": "02",
    "weekday_code": "2"
  },
  {
    "record_type_id": "YS",
    "data_division": "3",
    "data_created_date": "2025-02-03",
    "event_year": "2025",
    "event_date": "02-01",
    "racecourse_code": "05",
    "event_round": "01",
    "event_day": "01",
    "weekday_code": "1"
  },
  {
    "record_type_id": "YS",
    "data_division": "3",
    "data_created_date": "2025-02-03",
    "event_year": "2025",
    "event_date": "02-01",
    "racecourse_code": "08",
    "event_round": "01",
    "event_day": "01",
    "weekday_code": "1"
  },
  {
    "record_type_id": "YS",
    "data_division": "3",
    "data_created_date": "2025-02-03",
    "event_year": "2025",
    "event_date": "02-01",
    "racecourse_code": "10",
    "event_round": "01",
    "event_day": "03",
    "weekday_code": "1"
  },
  {
    "record_type_id": "YS",
    "data_division": "3",
    "data_created_date": "2025-02-03",
    "event_year": "2025",
    "event_date": "02-02",
    "racecourse_code": "05",
    "event_round": "01",
    "event_day": "02",
    "weekday_code": "2"
  },
  {
    "record_type_id": "YS",
    "data_division": "3",
    "data_created_date": "2025-02-03",
    "event_year": "2025",
    "event_date": "02-02",
    "racecourse_code": "08",
    "event_round": "01",
    "event_day": "02",
    "weekday_code": "2"
  },
  {
    "record_type_id": "YS",
    "data_division": "3",
    "data_created_date": "2025-02-03",
    "event_year": "2025",
    "event_date": "02-02",
    "racecourse_code": "10",
    "event_round": "01",
    "event_day": "04",
    "weekday_code": "2"
  },
  {
    "record_type_id": "YS",
    "data_division": "3",
    "data_created_date": "2025-02-11",
    "event_year": "2025",
    "event_date": "02-08",
    "racecourse_code": "05",
    "event_round": "01",
    "event_day": "03",
    "weekday_code": "1"
  },
  {
    "record_type_id": "YS",
    "data_division": "9",
    "data_created_date": "2025-02-11",
    "event_year": "2025",
    "event_date": "02-08",
    "racecourse_code": "08",
    "event_round": "01",
    "event_day": "03",
    "weekday_code": "1"
  },
  {
    "record_type_id": "YS",
    "data_division": "3",
    "data_created_date": "2025-02-11",
    "event_year": "2025",
    "event_date": "02-08",
    "racecourse_code": "10",
    "event_round": "01",
    "event_day": "05",
    "weekday_code": "1"
  },
  {
    "record_type_id": "YS",
    "data_division": "3",
    "data_created_date": "2025-02-11",
    "event_year": "2025",
    "event_date": "02-09",
    "racecourse_code": "05",
    "event_round": "01",
    "event_day": "04",
    "weekday_code": "2"
  },
  {
    "record_type_id": "YS",
    "data_division": "3",
    "data_created_date": "2025-02-11",
    "event_year": "2025",
    "event_date": "02-09",
    "racecourse_code": "08",
    "event_round": "01",
    "event_day": "04",
    "weekday_code": "2"
  },
  {
    "record_type_id": "YS",
    "data_division": "3",
    "data_created_date": "2025-02-11",
    "event_year": "2025",
    "event_date": "02-09",
    "racecourse_code": "10",
    "event_round": "01",
    "event_day": "06",
    "weekday_code": "2"
  },
  {
    "record_type_id": "YS",
    "data_division": "3",
    "data_created_date": "2025-02-11",
    "event_year": "2025",
    "event_date": "02-10",
    "racecourse_code": "08",
    "event_round": "01",
    "event_day": "03",
    "weekday_code": "4"
  },
  {
    "record_type_id": "YS",
    "data_division": "3",
    "data_created_date": "2025-02-17",
    "event_year": "2025",
    "event_date": "02-15",
    "racecourse_code": "05",
    "event_round": "01",
    "event_day": "05",
    "weekday_code": "1"
  },
  {
    "record_type_id": "YS",
    "data_division": "3",
    "data_created_date": "2025-02-17",
    "event_year": "2025",
    "event_date": "02-15",
    "racecourse_code": "08",
    "event_round": "01",
    "event_day": "05",
    "weekday_code": "1"
  },
  {
    "record_type_id": "YS",
    "data_division": "3",
    "data_created_date": "2025-02-17",
    "event_year": "2025",
    "event_date": "02-15",
    "racecourse_code": "10",
    "event_round": "01",
    "event_day": "07",
    "weekday_code": "1"
  },
  {
    "record_type_id": "YS",
    "data_division": "3",
    "data_created_date": "2025-02-17",
    "event_year": "2025",
    "event_date": "02-16",
    "racecourse_code": "05",
    "event_round": "01",
    "event_day": "06",
    "weekday_code": "2"
  },
  {
    "record_type_id": "YS",
    "data_division": "3",
    "data_created_date": "2025-02-17",
    "event_year": "2025",
    "event_date": "02-16",
    "racecourse_code": "08",
    "event_round": "01",
    "event_day": "06",
    "weekday_code": "2"
  },
  {
    "record_type_id": "YS",
    "data_division": "3",
    "data_created_date": "2025-02-17",
    "event_year": "2025",
    "event_date": "02-16",
    "racecourse_code": "10",
    "event_round": "01",
    "event_day": "08",
    "weekday_code": "2"
  },
  {
    "record_type_id": "YS",
    "data_division": "3",
    "data_created_date": "2025-02-24",
    "event_year": "2025",
    "event_date": "02-22",
    "racecourse_code": "05",
    "event_round": "01",
    "event_day": "07",
    "weekday_code": "1"
  },
  {
    "record_type_id": "YS",
    "data_division": "3",
    "data_created_date": "2025-02-24",
    "event_year": "2025",
    "event_date": "02-22",
    "racecourse_code": "08",
    "event_round": "01",
    "event_day": "07",
    "weekday_code": "1"
  },
  {
    "record_type_id": "YS",
    "data_division": "3",
    "data_created_date": "2025-02-24",
    "event_year": "2025",
    "event_date": "02-22",
    "racecourse_code": "10",
    "event_round": "01",
    "event_day": "09",
    "weekday_code": "1"
  },
  {
    "record_type_id": "YS",
    "data_division": "3",
    "data_created_date": "2025-02-24",
    "event_year": "2025",
    "event_date": "02-23",
    "racecourse_code": "05",
    "event_round": "01",
    "event_day": "08",
    "weekday_code": "3"
  },
  {
    "record_type_id": "YS",
    "data_division": "3",
    "data_created_date": "2025-02-24",
    "event_year": "2025",
    "event_date": "02-23",
    "racecourse_code": "08",
    "event_round": "01",
    "event_day": "08",
    "weekday_code": "3"
  },
  {
    "record_type_id": "YS",
    "data_division": "3",
    "data_created_date": "2025-02-24",
    "event_year": "2025",
    "event_date": "02-23",
    "racecourse_code": "10",
    "event_round": "01",
    "event_day": "10",
    "weekday_code": "3"
  },
  {
    "record_type_id": "YS",
    "data_division": "3",
    "data_created_date": "2025-03-03",
    "event_year": "2025",
    "event_date": "03-01",
    "racecourse_code": "06",
    "event_round": "02",
    "event_day": "01",
    "weekday_code": "1"
  },
  {
    "record_type_id": "YS",
    "data_division": "3",
    "data_created_date": "2025-03-03",
    "event_year": "2025",
    "event_date": "03-01",
    "racecourse_code": "09",
    "event_round": "01",
    "event_day": "01",
    "weekday_code": "1"
  },
  {
    "record_type_id": "YS",
    "data_division": "3",
    "data_created_date": "2025-03-03",
    "event_year": "2025",
    "event_date": "03-01",
    "racecourse_code": "10",
    "event_round": "01",
    "event_day": "11",
    "weekday_code": "1"
  },
  {
    "record_type_id": "YS",
    "data_division": "3",
    "data_created_date": "2025-03-03",
    "event_year": "2025",
    "event_date": "03-02",
    "racecourse_code": "06",
    "event_round": "02",
    "event_day": "02",
    "weekday_code": "2"
  },
  {
    "record_type_id": "YS",
    "data_division": "3",
    "data_created_date": "2025-03-03",
    "event_year": "2025",
    "event_date": "03-02",
    "racecourse_code": "09",
    "event_round": "01",
    "event_day": "02",
    "weekday_code": "2"
  },
  {
    "record_type_id": "YS",
    "data_division": "3",
    "data_created_date": "2025-03-03",
    "event_year": "2025",
    "event_date": "03-02",
    "racecourse_code": "10",
    "event_round": "01",
    "event_day": "12",
    "weekday_code": "2"
  },
  {
    "record_type_id": "YS",
    "data_division": "3",
    "data_created_date": "2025-03-10",
    "event_year": "2025",
    "event_date": "03-08",
    "racecourse_code": "06",
    "event_round": "02",
    "event_day": "03",
    "weekday_code": "1"
  },
  {
    "record_type_id": "YS",
    "data_division": "3",
    "data_created_date": "2025-03-10",
    "event_year": "2025",
    "event_date": "03-08",
    "racecourse_code": "09",
    "event_round": "01",
    "event_day": "03",
    "weekday_code": "1"
  },
  {
    "record_type_id": "YS",
    "data_division": "3",
    "data_created_date": "2025-03-10",
    "event_year": "2025",
    "event_date": "03-09",
    "racecourse_code": "06",
    "event_round": "02",
    "event_day": "04",
    "weekday_code": "2"
  },
  {
    "record_type_id": "YS",
    "data_division": "3",
    "data_created_date": "2025-03-10",
    "event_year": "2025",
    "event_date": "03-09",
    "racecourse_code": "09",
    "event_round": "01",
    "event_day": "04",
    "weekday_code": "2"
  },
  {
    "record_type_id": "YS",
    "data_division": "3",
    "data_created_date": "2025-03-17",
    "event_year": "2025",
    "event_date": "03-15",
    "racecourse_code": "06",
    "event_round": "02",
    "event_day": "05",
    "weekday_code": "1"
  },
  {
    "record_type_id": "YS",
    "data_division": "3",
    "data_created_date": "2025-03-17",
    "event_year": "2025",
    "event_date": "03-15",
    "racecourse_code": "07",
    "event_round": "02",
    "event_day": "01",
    "weekday_code": "1"
  },
  {
    "record_type_id": "YS",
    "data_division": "3",
    "data_created_date": "2025-03-17",
    "event_year": "2025",
    "event_date": "03-15",
    "racecourse_code": "09",
    "event_round": "01",
    "event_day": "05",
    "weekday_code": "1"
  },
  {
    "record_type_id": "YS",
    "data_division": "3",
    "data_created_date": "2025-03-17",
    "event_year": "2025",
    "event_date": "03-16",
    "racecourse_code": "06",
    "event_round": "02",
    "event_day": "06",
    "weekday_code": "2"
  },
  {
    "record_type_id": "YS",
    "data_division": "3",
    "data_created_date": "2025-03-17",
    "event_year": "2025",
    "event_date": "03-16",
    "racecourse_code": "07",
    "event_round": "02",
    "event_day": "02",
    "weekday_code": "2"
  },
  {
    "record_type_id": "YS",
    "data_division": "3",
    "data_created_date": "2025-03-17",
    "event_year": "2025",
    "event_date": "03-16",
    "racecourse_code": "09",
    "event_round": "01",
    "event_day": "06",
    "weekday_code": "2"
  },
  {
    "record_type_id": "YS",
    "data_division": "3",
    "data_created_date": "2025-03-24",
    "event_year": "2025",
    "event_date": "03-22",
    "racecourse_code": "06",
    "event_round": "02",
    "event_day": "07",
    "weekday_code": "1"
  },
  {
    "record_type_id": "YS",
    "data_division": "3",
    "data_created_date": "2025-03-24",
    "event_year": "2025",
    "event_date": "03-22",
    "racecourse_code": "07",
    "event_round": "02",
    "event_day": "03",
    "weekday_code": "1"
  },
  {
    "record_type_id": "YS",
    "data_division": "3",
    "data_created_date": "2025-03-24",
    "event_year": "2025",
    "event_date": "03-22",
    "racecourse_code": "09",
    "event_round": "01",
    "event_day": "07",
    "weekday_code": "1"
  },
  {
    "record_type_id": "YS",
    "data_division": "3",
    "data_created_date": "2025-03-24",
    "event_year": "2025",
    "event_date": "03-23",
    "racecourse_code": "06",
    "event_round": "02",
    "event_day": "08",
    "weekday_code": "2"
  },
  {
    "record_type_id": "YS",
    "data_division": "3",
    "data_created_date": "2025-03-24",
    "event_year": "2025",
    "event_date": "03-23",
    "racecourse_code": "07",
    "event_round": "02",
    "event_day": "04",
    "weekday_code": "2"
  },
  {
    "record_type_id": "YS",
    "data_division": "3",
    "data_created_date": "2025-03-24",
    "event_year": "2025",
    "event_date": "03-23",
    "racecourse_code": "09",
    "event_round": "01",
    "event_day": "08",
    "weekday_code": "2"
  },
  {
    "record_type_id": "YS",
    "data_division": "3",
    "data_created_date": "2025-03-31",
    "event_year": "2025",
    "event_date": "03-29",
    "racecourse_code": "06",
    "event_round": "03",
    "event_day": "01",
    "weekday_code": "1"
  },
  {
    "record_type_id": "YS",
    "data_division": "3",
    "data_created_date": "2025-03-31",
    "event_year": "2025",
    "event_date": "03-29",
    "racecourse_code": "07",
    "event_round": "02",
    "event_day": "05",
    "weekday_code": "1"
  },
  {
    "record_type_id": "YS",
    "data_division": "3",
    "data_created_date": "2025-03-31",
    "event_year": "2025",
    "event_date": "03-29",
    "racecourse_code": "09",
    "event_round": "02",
    "event_day": "01",
    "weekday_code": "1"
  },
  {
    "record_type_id": "YS",
    "data_division": "3",
    "data_created_date": "2025-03-31",
    "event_year": "2025",
    "event_date": "03-30",
    "racecourse_code": "06",
    "event_round": "03",
    "event_day": "02",
    "weekday_code": "2"
  },
  {
    "record_type_id": "YS",
    "data_division": "3",
    "data_created_date": "2025-03-31",
    "event_year": "2025",
    "event_date": "03-30",
    "racecourse_code": "07",
    "event_round": "02",
    "event_day": "06",
    "weekday_code": "2"
  },
  {
    "record_type_id": "YS",
    "data_division": "3",
    "data_created_date": "2025-03-31",
    "event_year": "2025",
    "event_date": "03-30",
    "racecourse_code": "09",
    "event_round": "02",
    "event_day": "02",
    "weekday_code": "2"
  },
  {
    "record_type_id": "YS",
    "data_division": "3",
    "data_created_date": "2025-04-07",
    "event_year": "2025",
    "event_date": "04-05",
    "racecourse_code": "06",
    "event_round": "03",
    "event_day": "03",
    "weekday_code": "1"
  },
  {
    "record_type_id": "YS",
    "data_division": "3",
    "data_created_date": "2025-04-07",
    "event_year": "2025",
    "event_date": "04-05",
    "racecourse_code": "09",
    "event_round": "02",
    "event_day": "03",
    "weekday_code": "1"
  },
  {
    "record_type_id": "YS",
    "data_division": "3",
    "data_created_date": "2025-04-07",
    "event_year": "2025",
    "event_date": "04-06",
    "racecourse_code": "06",
    "event_round": "03",
    "event_day": "04",
    "weekday_code": "2"
  },
  {
    "record_type_id": "YS",
    "data_division": "3",
    "data_created_date": "2025-04-07",
    "event_year": "2025",
    "event_date": "04-06",
    "racecourse_code": "09",
    "event_round": "02",
    "event_day": "04",
    "weekday_code": "2"
  },
  {
    "record_type_id": "YS",
    "data_division": "2",
    "data_created_date": "2025-04-06",
    "event_year": "2025",
    "event_date": "04-12",
    "racecourse_code": "03",
    "event_round": "01",
    "event_day": "01",
    "weekday_code": "1"
  },
  {
    "record_type_id": "YS",
    "data_division": "2",
    "data_created_date": "2025-04-06",
    "event_year": "2025",
    "event_date": "04-12",
    "racecourse_code": "06",
    "event_round": "03",
    "event_day": "05",
    "weekday_code": "1"
  },
  {
    "record_type_id": "YS",
    "data_division": "2",
    "data_created_date": "2025-04-06",
    "event_year": "2025",
    "event_date": "04-12",
    "racecourse_code": "09",
    "event_round": "02",
    "event_day": "05",
    "weekday_code": "1"
  },
  {
    "record_type_id": "YS",
    "data_division": "2",
    "data_created_date": "2025-04-06",
    "event_year": "2025",
    "event_date": "04-13",
    "racecourse_code": "03",
    "event_round": "01",
    "event_day": "02",
    "weekday_code": "2"
  },
  {
    "record_type_id": "YS",
    "data_division": "2",
    "data_created_date": "2025-04-06",
    "event_year": "2025",
    "event_date": "04-13",
    "racecourse_code": "06",
    "event_round": "03",
    "event_day": "06",
    "weekday_code": "2"
  },
  {
    "record_type_id": "YS",
    "data_division": "2",
    "data_created_date": "2025-04-06",
    "event_year": "2025",
    "event_date": "04-13",
    "racecourse_code": "09",
    "event_round": "02",
    "event_day": "06",
    "weekday_code": "2"
  },
  {
    "record_type_id": "YS",
    "data_division": "1",
    "data_created_date": "2024-12-20",
    "event_year": "2025",
    "event_date": "04-19",
    "racecourse_code": "03",
    "event_round": "01",
    "event_day": "03",
    "weekday_code": "1"
  },
  {
    "record_type_id": "YS",
    "data_division": "1",
    "data_created_date": "2024-12-20",
    "event_year": "2025",
    "event_date": "04-19",
    "racecourse_code": "06",
    "event_round": "03",
    "event_day": "07",
    "weekday_code": "1"
  },
  {
    "record_type_id": "YS",
    "data_division": "1",
    "data_created_date": "2024-12-20",
    "event_year": "2025",
    "event_date": "04-19",
    "racecourse_code": "09",
    "event_round": "02",
    "event_day": "07",
    "weekday_code": "1"
  },
  {
    "record_type_id": "YS",
    "data_division": "1",
    "data_created_date": "2024-12-20",
    "event_year": "2025",
    "event_date": "04-20",
    "racecourse_code": "03",
    "event_round": "01",
    "event_day": "04",
    "weekday_code": "2"
  },
  {
    "record_type_id": "YS",
    "data_division": "2",
    "data_created_date": "2025-04-06",
    "event_year": "2025",
    "event_date": "04-20",
    "racecourse_code": "06",
    "event_round": "03",
    "event_day": "08",
    "weekday_code": "2"
  },
  {
    "record_type_id": "YS",
    "data_division": "1",
    "data_created_date": "2024-12-20",
    "event_year": "2025",
    "event_date": "04-20",
    "racecourse_code": "09",
    "event_round": "02",
    "event_day": "08",
    "weekday_code": "2"
  },
  {
    "record_type_id": "YS",
    "data_division": "1",
    "data_created_date": "2024-12-20",
    "event_year": "2025",
    "event_date": "04-26",
    "racecourse_code": "03",
    "event_round": "01",
    "event_day": "05",
    "weekday_code": "1"
  },
  {
    "record_type_id": "YS",
    "data_division": "1",
    "data_created_date": "2024-12-20",
    "event_year": "2025",
    "event_date": "04-26",
    "racecourse_code": "05",
    "event_round": "02",
    "event_day": "01",
    "weekday_code": "1"
  },
  {
    "record_type_id": "YS",
    "data_division": "1",
    "data_created_date": "2024-12-20",
    "event_year": "2025",
    "event_date": "04-26",
    "racecourse_code": "08",
    "event_round": "02",
    "event_day": "01",
    "weekday_code": "1"
  },
  {
    "record_type_id": "YS",
    "data_division": "1",
    "data_created_date": "2024-12-20",
    "event_year": "2025",
    "event_date": "04-27",
    "racecourse_code": "03",
    "event_round": "01",
    "event_day": "06",
    "weekday_code": "2"
  },
  {
    "record_type_id": "YS",
    "data_division": "1",
    "data_created_date": "2024-12-20",
    "event_year": "2025",
    "event_date": "04-27",
    "racecourse_code": "05",
    "event_round": "02",
    "event_day": "02",
    "weekday_code": "2"
  },
  {
    "record_type_id": "YS",
    "data_division": "1",
    "data_created_date": "2024-12-20",
    "event_year": "2025",
    "event_date": "04-27",
    "racecourse_code": "08",
    "event_round": "02",
    "event_day": "02",
    "weekday_code": "2"
  },
  {
    "record_type_id": "YS",
    "data_division": "1",
    "data_created_date": "2024-12-20",
    "event_year": "2025",
    "event_date": "05-03",
    "racecourse_code": "04",
    "event_round": "01",
    "event_day": "01",
    "weekday_code": "3"
  },
  {
    "record_type_id": "YS",
    "data_division": "1",
    "data_created_date": "2024-12-20",
    "event_year": "2025",
    "event_date": "05-03",
    "racecourse_code": "05",
    "event_round": "02",
    "event_day": "03",
    "weekday_code": "3"
  },
  {
    "record_type_id": "YS",
    "data_division": "1",
    "data_created_date": "2024-12-20",
    "event_year": "2025",
    "event_date": "05-03",
    "racecourse_code": "08",
    "event_round": "02",
    "event_day": "03",
    "weekday_code": "3"
  },
  {
    "record_type_id": "YS",
    "data_division": "1",
    "data_created_date": "2024-12-20",
    "event_year": "2025",
    "event_date": "05-04",
    "racecourse_code": "04",
    "event_round": "01",
    "event_day": "02",
    "weekday_code": "3"
  },
  {
    "record_type_id": "YS",
    "data_division": "1",
    "data_created_date": "2024-12-20",
    "event_year": "2025",
    "event_date": "05-04",
    "racecourse_code": "05",
    "event_round": "02",
    "event_day": "04",
    "weekday_code": "3"
  },
  {
    "record_type_id": "YS",
    "data_division": "1",
    "data_created_date": "2024-12-20",
    "event_year": "2025",
    "event_date": "05-04",
    "racecourse_code": "08",
    "event_round": "02",
    "event_day": "04",
    "weekday_code": "3"
  },
  {
    "record_type_id": "YS",
    "data_division": "1",
    "data_created_date": "2024-12-20",
    "event_year": "2025",
    "event_date": "05-10",
    "racecourse_code": "04",
    "event_round": "01",
    "event_day": "03",
    "weekday_code": "1"
  },
  {
    "record_type_id": "YS",
    "data_division": "1",
    "data_created_date": "2024-12-20",
    "event_year": "2025",
    "event_date": "05-10",
    "racecourse_code": "05",
    "event_round": "02",
    "event_day": "05",
    "weekday_code": "1"
  },
  {
    "record_type_id": "YS",
    "data_division": "1",
    "data_created_date": "2024-12-20",
    "event_year": "2025",
    "event_date": "05-10",
    "racecourse_code": "08",
    "event_round": "02",
    "event_day": "05",
    "weekday_code": "1"
  },
  {
    "record_type_id": "YS",
    "data_division": "1",
    "data_created_date": "2024-12-20",
    "event_year": "2025",
    "event_date": "05-11",
    "racecourse_code": "04",
    "event_round": "01",
    "event_day": "04",
    "weekday_code": "2"
  },
  {
    "record_type_id": "YS",
    "data_division": "1",
    "data_created_date": "2024-12-20",
    "event_year": "2025",
    "event_date": "05-11",
    "racecourse_code": "05",
    "event_round": "02",
    "event_day": "06",
    "weekday_code": "2"
  },
  {
    "record_type_id": "YS",
    "data_division": "1",
    "data_created_date": "2024-12-20",
    "event_year": "2025",
    "event_date": "05-11",
    "racecourse_code": "08",
    "event_round": "02",
    "event_day": "06",
    "weekday_code": "2"
  },
  {
    "record_type_id": "YS",
    "data_division": "1",
    "data_created_date": "2024-12-20",
    "event_year": "2025",
    "event_date": "05-17",
    "racecourse_code": "04",
    "event_round": "01",
    "event_day": "05",
    "weekday_code": "1"
  },
  {
    "record_type_id": "YS",
    "data_division": "1",
    "data_created_date": "2024-12-20",
    "event_year": "2025",
    "event_date": "05-17",
    "racecourse_code": "05",
    "event_round": "02",
    "event_day": "07",
    "weekday_code": "1"
  },
  {
    "record_type_id": "YS",
    "data_division": "1",
    "data_created_date": "2024-12-20",
    "event_year": "2025",
    "event_date": "05-17",
    "racecourse_code": "08",
    "event_round": "02",
    "event_day": "07",
    "weekday_code": "1"
  },
  {
    "record_type_id": "YS",
    "data_division": "1",
    "data_created_date": "2024-12-20",
    "event_year": "2025",
    "event_date": "05-18",
    "racecourse_code": "04",
    "event_round": "01",
    "event_day": "06",
    "weekday_code": "2"
  },
  {
    "record_type_id": "YS",
    "data_division": "1",
    "data_created_date": "2024-12-20",
    "event_year": "2025",
    "event_date": "05-18",
    "racecourse_code": "05",
    "event_round": "02",
    "event_day": "08",
    "weekday_code": "2"
  },
  {
    "record_type_id": "YS",
    "data_division": "1",
    "data_created_date": "2024-12-20",
    "event_year": "2025",
    "event_date": "05-18",
    "racecourse_code": "08",
    "event_round": "02",
    "event_day": "08",
    "weekday_code": "2"
  },
  {
    "record_type_id": "YS",
    "data_division": "1",
    "data_created_date": "2024-12-20",
    "event_year": "2025",
    "event_date": "05-24",
    "racecourse_code": "04",
    "event_round": "01",
    "event_day": "07",
    "weekday_code": "1"
  },
  {
    "record_type_id": "YS",
    "data_division": "1",
    "data_created_date": "2024-12-20",
    "event_year": "2025",
    "event_date": "05-24",
    "racecourse_code": "05",
    "event_round": "02",
    "event_day": "09",
    "weekday_code": "1"
  },
  {
    "record_type_id": "YS",
    "data_division": "1",
    "data_created_date": "2024-12-20",
    "event_year": "2025",
    "event_date": "05-24",
    "racecourse_code": "08",
    "event_round": "02",
    "event_day": "09",
    "weekday_code": "1"
  },
  {
    "record_type_id": "YS",
    "data_division": "1",
    "data_created_date": "2024-12-20",
    "event_year": "2025",
    "event_date": "05-25",
    "racecourse_code": "04",
    "event_round": "01",
    "event_day": "08",
    "weekday_code": "2"
  },
  {
    "record_type_id": "YS",
    "data_division": "1",
    "data_created_date": "2024-12-20",
    "event_year": "2025",
    "event_date": "05-25",
    "racecourse_code": "05",
    "event_round": "02",
    "event_day": "10",
    "weekday_code": "2"
  },
  {
    "record_type_id": "YS",
    "data_division": "1",
    "data_created_date": "2024-12-20",
    "event_year": "2025",
    "event_date": "05-25",
    "racecourse_code": "08",
    "event_round": "02",
    "event_day": "10",
    "weekday_code": "2"
  },
  {
    "record_type_id": "YS",
    "data_division": "1",
    "data_created_date": "2024-12-20",
    "event_year": "2025",
    "event_date": "05-31",
    "racecourse_code": "05",
    "event_round": "02",
    "event_day": "11",
    "weekday_code": "1"
  },
  {
    "record_type_id": "YS",
    "data_division": "1",
    "data_created_date": "2024-12-20",
    "event_year": "2025",
    "event_date": "05-31",
    "racecourse_code": "08",
    "event_round": "02",
    "event_day": "11",
    "weekday_code": "1"
  },
  {
    "record_type_id": "YS",
    "data_division": "1",
    "data_created_date": "2024-12-20",
    "event_year": "2025",
    "event_date": "06-01",
    "racecourse_code": "05",
    "event_round": "02",
    "event_day": "12",
    "weekday_code": "2"
  },
  {
    "record_type_id": "YS",
    "data_division": "1",
    "data_created_date": "2024-12-20",
    "event_year": "2025",
    "event_date": "06-01",
    "racecourse_code": "08",
    "event_round": "02",
    "event_day": "12",
    "weekday_code": "2"
  },
  {
    "record_type_id": "YS",
    "data_division": "1",
    "data_created_date": "2024-12-20",
    "event_year": "2025",
    "event_date": "06-07",
    "racecourse_code": "05",
    "event_round": "03",
    "event_day": "01",
    "weekday_code": "1"
  },
  {
    "record_type_id": "YS",
    "data_division": "1",
    "data_created_date": "2024-12-20",
    "event_year": "2025",
    "event_date": "06-07",
    "racecourse_code": "09",
    "event_round": "03",
    "event_day": "01",
    "weekday_code": "1"
  },
  {
    "record_type_id": "YS",
    "data_division": "1",
    "data_created_date": "2024-12-20",
    "event_year": "2025",
    "event_date": "06-08",
    "racecourse_code": "05",
    "event_round": "03",
    "event_day": "02",
    "weekday_code": "2"
  },
  {
    "record_type_id": "YS",
    "data_division": "1",
    "data_created_date": "2024-12-20",
    "event_year": "2025",
    "event_date": "06-08",
    "racecourse_code": "09",
    "event_round": "03",
    "event_day": "02",
    "weekday_code": "2"
  },
  {
    "record_type_id": "YS",
    "data_division": "1",
    "data_created_date": "2024-12-20",
    "event_year": "2025",
    "event_date": "06-14",
    "racecourse_code": "02",
    "event_round": "01",
    "event_day": "01",
    "weekday_code": "1"
  },
  {
    "record_type_id": "YS",
    "data_division": "1",
    "data_created_date": "2024-12-20",
    "event_year": "2025",
    "event_date": "06-14",
    "racecourse_code": "05",
    "event_round": "03",
    "event_day": "03",
    "weekday_code": "1"
  },
  {
    "record_type_id": "YS",
    "data_division": "1",
    "data_created_date": "2024-12-20",
    "event_year": "2025",
    "event_date": "06-14",
    "racecourse_code": "09",
    "event_round": "03",
    "event_day": "03",
    "weekday_code": "1"
  },
  {
    "record_type_id": "YS",
    "data_division": "1",
    "data_created_date": "2024-12-20",
    "event_year": "2025",
    "event_date": "06-15",
    "racecourse_code": "02",
    "event_round": "01",
    "event_day": "02",
    "weekday_code": "2"
  },
  {
    "record_type_id": "YS",
    "data_division": "1",
    "data_created_date": "2024-12-20",
    "event_year": "2025",
    "event_date": "06-15",
    "racecourse_code": "05",
    "event_round": "03",
    "event_day": "04",
    "weekday_code": "2"
  },
  {
    "record_type_id": "YS",
    "data_division": "1",
    "data_created_date": "2024-12-20",
    "event_year": "2025",
    "event_date": "06-15",
    "racecourse_code": "09",
    "event_round": "03",
    "event_day": "04",
    "weekday_code": "2"
  },
  {
    "record_type_id": "YS",
    "data_division": "1",
    "data_created_date": "2024-12-20",
    "event_year": "2025",
    "event_date": "06-21",
    "racecourse_code": "02",
    "event_round": "01",
    "event_day": "03",
    "weekday_code": "1"
  },
  {
    "record_type_id": "YS",
    "data_division": "1",
    "data_created_date": "2024-12-20",
    "event_year": "2025",
    "event_date": "06-21",
    "racecourse_code": "05",
    "event_round": "03",
    "event_day": "05",
    "weekday_code": "1"
  },
  {
    "record_type_id": "YS",
    "data_division": "1",
    "data_created_date": "2024-12-20",
    "event_year": "2025",
    "event_date": "06-21",
    "racecourse_code": "09",
    "event_round": "03",
    "event_day": "05",
    "weekday_code": "1"
  },
  {
    "record_type_id": "YS",
    "data_division": "1",
    "data_created_date": "2024-12-20",
    "event_year": "2025",
    "event_date": "06-22",
    "racecourse_code": "02",
    "event_round": "01",
    "event_day": "04",
    "weekday_code": "2"
  },
  {
    "record_type_id": "YS",
    "data_division": "1",
    "data_created_date": "2024-12-20",
    "event_year": "2025",
    "event_date": "06-22",
    "racecourse_code": "05",
    "event_round": "03",
    "event_day": "06",
    "weekday_code": "2"
  },
  {
    "record_type_id": "YS",
    "data_division": "1",
    "data_created_date": "2024-12-20",
    "event_year": "2025",
    "event_date": "06-22",
    "racecourse_code": "09",
    "event_round": "03",
    "event_day": "06",
    "weekday_code": "2"
  },
  {
    "record_type_id": "YS",
    "data_division": "1",
    "data_created_date": "2024-12-20",
    "event_year": "2025",
    "event_date": "06-28",
    "racecourse_code": "02",
    "event_round": "01",
    "event_day": "05",
    "weekday_code": "1"
  },
  {
    "record_type_id": "YS",
    "data_division": "1",
    "data_created_date": "2024-12-20",
    "event_year": "2025",
    "event_date": "06-28",
    "racecourse_code": "03",
    "event_round": "02",
    "event_day": "01",
    "weekday_code": "1"
  },
  {
    "record_type_id": "YS",
    "data_division": "1",
    "data_created_date": "2024-12-20",
    "event_year": "2025",
    "event_date": "06-28",
    "racecourse_code": "10",
    "event_round": "02",
    "event_day": "01",
    "weekday_code": "1"
  },
  {
    "record_type_id": "YS",
    "data_division": "1",
    "data_created_date": "2024-12-20",
    "event_year": "2025",
    "event_date": "06-29",
    "racecourse_code": "02",
    "event_round": "01",
    "event_day": "06",
    "weekday_code": "2"
  },
  {
    "record_type_id": "YS",
    "data_division": "1",
    "data_created_date": "2024-12-20",
    "event_year": "2025",
    "event_date": "06-29",
    "racecourse_code": "03",
    "event_round": "02",
    "event_day": "02",
    "weekday_code": "2"
  },
  {
    "record_type_id": "YS",
    "data_division": "1",
    "data_created_date": "2024-12-20",
    "event_year": "2025",
    "event_date": "06-29",
    "racecourse_code": "10",
    "event_round": "02",
    "event_day": "02",
    "weekday_code": "2"
  },
  {
    "record_type_id": "YS",
    "data_division": "1",
    "data_created_date": "2024-12-20",
    "event_year": "2025",
    "event_date": "07-05",
    "racecourse_code": "02",
    "event_round": "01",
    "event_day": "07",
    "weekday_code": "1"
  },
  {
    "record_type_id": "YS",
    "data_division": "1",
    "data_created_date": "2024-12-20",
    "event_year": "2025",
    "event_date": "07-05",
    "racecourse_code": "03",
    "event_round": "02",
    "event_day": "03",
    "weekday_code": "1"
  },
  {
    "record_type_id": "YS",
    "data_division": "1",
    "data_created_date": "2024-12-20",
    "event_year": "2025",
    "event_date": "07-05",
    "racecourse_code": "10",
    "event_round": "02",
    "event_day": "03",
    "weekday_code": "1"
  },
  {
    "record_type_id": "YS",
    "data_division": "1",
    "data_created_date": "2024-12-20",
    "event_year": "2025",
    "event_date": "07-06",
    "racecourse_code": "02",
    "event_round": "01",
    "event_day": "08",
    "weekday_code": "2"
  },
  {
    "record_type_id": "YS",
    "data_division": "1",
    "data_created_date": "2024-12-20",
    "event_year": "2025",
    "event_date": "07-06",
    "racecourse_code": "03",
    "event_round": "02",
    "event_day": "04",
    "weekday_code": "2"
  },
  {
    "record_type_id": "YS",
    "data_division": "1",
    "data_created_date": "2024-12-20",
    "event_year": "2025",
    "event_date": "07-06",
    "racecourse_code": "10",
    "event_round": "02",
    "event_day": "04",
    "weekday_code": "2"
  },
  {
    "record_type_id": "YS",
    "data_division": "1",
    "data_created_date": "2024-12-20",
    "event_year": "2025",
    "event_date": "07-12",
    "racecourse_code": "02",
    "event_round": "01",
    "event_day": "09",
    "weekday_code": "1"
  },
  {
    "record_type_id": "YS",
    "data_division": "1",
    "data_created_date": "2024-12-20",
    "event_year": "2025",
    "event_date": "07-12",
    "racecourse_code": "03",
    "event_round": "02",
    "event_day": "05",
    "weekday_code": "1"
  },
  {
    "record_type_id": "YS",
    "data_division": "1",
    "data_created_date": "2024-12-20",
    "event_year": "2025",
    "event_date": "07-12",
    "racecourse_code": "10",
    "event_round": "02",
    "event_day": "05",
    "weekday_code": "1"
  },
  {
    "record_type_id": "YS",
    "data_division": "1",
    "data_created_date": "2024-12-20",
    "event_year": "2025",
    "event_date": "07-13",
    "racecourse_code": "02",
    "event_round": "01",
    "event_day": "10",
    "weekday_code": "2"
  },
  {
    "record_type_id": "YS",
    "data_division": "1",
    "data_created_date": "2024-12-20",
    "event_year": "2025",
    "event_date": "07-13",
    "racecourse_code": "03",
    "event_round": "02",
    "event_day": "06",
    "weekday_code": "2"
  },
  {
    "record_type_id": "YS",
    "data_division": "1",
    "data_created_date": "2024-12-20",
    "event_year": "2025",
    "event_date": "07-13",
    "racecourse_code": "10",
    "event_round": "02",
    "event_day": "06",
    "weekday_code": "2"
  },
  {
    "record_type_id": "YS",
    "data_division": "1",
    "data_created_date": "2024-12-20",
    "event_year": "2025",
    "event_date": "07-19",
    "racecourse_code": "02",
    "event_round": "01",
    "event_day": "11",
    "weekday_code": "1"
  },
  {
    "record_type_id": "YS",
    "data_division": "1",
    "data_created_date": "2024-12-20",
    "event_year": "2025",
    "event_date": "07-19",
    "racecourse_code": "03",
    "event_round": "02",
    "event_day": "07",
    "weekday_code": "1"
  },
  {
    "record_type_id": "YS",
    "data_division": "1",
    "data_created_date": "2024-12-20",
    "event_year": "2025",
    "event_date": "07-19",
    "racecourse_code": "10",
    "event_round": "02",
    "event_day": "07",
    "weekday_code": "1"
  },
  {
    "record_type_id": "YS",
    "data_division": "1",
    "data_created_date": "2024-12-20",
    "event_year": "2025",
    "event_date": "07-20",
    "racecourse_code": "02",
    "event_round": "01",
    "event_day": "12",
    "weekday_code": "2"
  },
  {
    "record_type_id": "YS",
    "data_division": "1",
    "data_created_date": "2024-12-20",
    "event_year": "2025",
    "event_date": "07-20",
    "racecourse_code": "03",
    "event_round": "02",
    "event_day": "08",
    "weekday_code": "2"
  },
  {
    "record_type_id": "YS",
    "data_division": "1",
    "data_created_date": "2024-12-20",
    "event_year": "2025",
    "event_date": "07-20",
    "racecourse_code": "10",
    "event_round": "02",
    "event_day": "08",
    "weekday_code": "2"
  },
  {
    "record_type_id": "YS",
    "data_division": "1",
    "data_created_date": "2024-12-20",
    "event_year": "2025",
    "event_date": "07-26",
    "racecourse_code": "01",
    "event_round": "01",
    "event_day": "01",
    "weekday_code": "1"
  },
  {
    "record_type_id": "YS",
    "data_division": "1",
    "data_created_date": "2024-12-20",
    "event_year": "2025",
    "event_date": "07-26",
    "racecourse_code": "04",
    "event_round": "02",
    "event_day": "01",
    "weekday_code": "1"
  },
  {
    "record_type_id": "YS",
    "data_division": "1",
    "data_created_date": "2024-12-20",
    "event_year": "2025",
    "event_date": "07-26",
    "racecourse_code": "07",
    "event_round": "03",
    "event_day": "01",
    "weekday_code": "1"
  },
  {
    "record_type_id": "YS",
    "data_division": "1",
    "data_created_date": "2024-12-20",
    "event_year": "2025",
    "event_date": "07-27",
    "racecourse_code": "01",
    "event_round": "01",
    "event_day": "02",
    "weekday_code": "2"
  },
  {
    "record_type_id": "YS",
    "data_division": "1",
    "data_created_date": "2024-12-20",
    "event_year": "2025",
    "event_date": "07-27",
    "racecourse_code": "04",
    "event_round": "02",
    "event_day": "02",
    "weekday_code": "2"
  },
  {
    "record_type_id": "YS",
    "data_division": "1",
    "data_created_date": "2024-12-20",
    "event_year": "2025",
    "event_date": "07-27",
    "racecourse_code": "07",
    "event_round": "03",
    "event_day": "02",
    "weekday_code": "2"
  },
  {
    "record_type_id": "YS",
    "data_division": "1",
    "data_created_date": "2024-12-20",
    "event_year": "2025",
    "event_date": "08-02",
    "racecourse_code": "01",
    "event_round": "01",
    "event_day": "03",
    "weekday_code": "1"
  },
  {
    "record_type_id": "YS",
    "data_division": "1",
    "data_created_date": "2024-12-20",
    "event_year": "2025",
    "event_date": "08-02",
    "racecourse_code": "04",
    "event_round": "02",
    "event_day": "03",
    "weekday_code": "1"
  },
  {
    "record_type_id": "YS",
    "data_division": "1",
    "data_created_date": "2024-12-20",
    "event_year": "2025",
    "event_date": "08-02",
    "racecourse_code": "07",
    "event_round": "03",
    "event_day": "03",
    "weekday_code": "1"
  },
  {
    "record_type_id": "YS",
    "data_division": "1",
    "data_created_date": "2024-12-20",
    "event_year": "2025",
    "event_date": "08-03",
    "racecourse_code": "01",
    "event_round": "01",
    "event_day": "04",
    "weekday_code": "2"
  },
  {
    "record_type_id": "YS",
    "data_division": "1",
    "data_created_date": "2024-12-20",
    "event_year": "2025",
    "event_date": "08-03",
    "racecourse_code": "04",
    "event_round": "02",
    "event_day": "04",
    "weekday_code": "2"
  },
  {
    "record_type_id": "YS",
    "data_division": "1",
    "data_created_date": "2024-12-20",
    "event_year": "2025",
    "event_date": "08-03",
    "racecourse_code": "07",
    "event_round": "03",
    "event_day": "04",
    "weekday_code": "2"
  },
  {
    "record_type_id": "YS",
    "data_division": "1",
    "data_created_date": "2024-12-20",
    "event_year": "2025",
    "event_date": "08-09",
    "racecourse_code": "01",
    "event_round": "01",
    "event_day": "05",
    "weekday_code": "1"
  },
  {
    "record_type_id": "YS",
    "data_division": "1",
    "data_created_date": "2024-12-20",
    "event_year": "2025",
    "event_date": "08-09",
    "racecourse_code": "04",
    "event_round": "02",
    "event_day": "05",
    "weekday_code": "1"
  },
  {
    "record_type_id": "YS",
    "data_division": "1",
    "data_created_date": "2024-12-20",
    "event_year": "2025",
    "event_date": "08-09",
    "racecourse_code": "07",
    "event_round": "03",
    "event_day": "05",
    "weekday_code": "1"
  },
  {
    "record_type_id": "YS",
    "data_division": "1",
    "data_created_date": "2024-12-20",
    "event_year": "2025",
    "event_date": "08-10",
    "racecourse_code": "01",
    "event_round": "01",
    "event_day": "06",
    "weekday_code": "2"
  },
  {
    "record_type_id": "YS",
    "data_division": "1",
    "data_created_date": "2024-12-20",
    "event_year": "2025",
    "event_date": "08-10",
    "racecourse_code": "04",
    "event_round": "02",
    "event_day": "06",
    "weekday_code": "2"
  },
  {
    "record_type_id": "YS",
    "data_division": "1",
    "data_created_date": "2024-12-20",
    "event_year": "2025",
    "event_date": "08-10",
    "racecourse_code": "07",
    "event_round": "03",
    "event_day": "06",
    "weekday_code": "2"
  },
  {
    "record_type_id": "YS",
    "data_division": "1",
    "data_created_date": "2024-12-20",
    "event_year": "2025",
    "event_date": "08-16",
    "racecourse_code": "01",
    "event_round": "01",
    "event_day": "07",
    "weekday_code": "1"
  },
  {
    "record_type_id": "YS",
    "data_division": "1",
    "data_created_date": "2024-12-20",
    "event_year": "2025",
    "event_date": "08-16",
    "racecourse_code": "04",
    "event_round": "02",
    "event_day": "07",
    "weekday_code": "1"
  },
  {
    "record_type_id": "YS",
    "data_division": "1",
    "data_created_date": "2024-12-20",
    "event_year": "2025",
    "event_date": "08-16",
    "racecourse_code": "07",
    "event_round": "03",
    "event_day": "07",
    "weekday_code": "1"
  },
  {
    "record_type_id": "YS",
    "data_division": "1",
    "data_created_date": "2024-12-20",
    "event_year": "2025",
    "event_date": "08-17",
    "racecourse_code": "01",
    "event_round": "01",
    "event_day": "08",
    "weekday_code": "2"
  },
  {
    "record_type_id": "YS",
    "data_division": "1",
    "data_created_date": "2024-12-20",
    "event_year": "2025",
    "event_date": "08-17",
    "racecourse_code": "04",
    "event_round": "02",
    "event_day": "08",
    "weekday_code": "2"
  },
  {
    "record_type_id": "YS",
    "data_division": "1",
    "data_created_date": "2024-12-20",
    "event_year": "2025",
    "event_date": "08-17",
    "racecourse_code": "07",
    "event_round": "03",
    "event_day": "08",
    "weekday_code": "2"
  },
  {
    "record_type_id": "YS",
    "data_division": "1",
    "data_created_date": "2024-12-20",
    "event_year": "2025",
    "event_date": "08-23",
    "racecourse_code": "01",
    "event_round": "02",
    "event_day": "01",
    "weekday_code": "1"
  },
  {
    "record_type_id": "YS",
    "data_division": "1",
    "data_created_date": "2024-12-20",
    "event_year": "2025",
    "event_date": "08-23",
    "racecourse_code": "04",
    "event_round": "03",
    "event_day": "01",
    "weekday_code": "1"
  },
  {
    "record_type_id": "YS",
    "data_division": "1",
    "data_created_date": "2024-12-20",
    "event_year": "2025",
    "event_date": "08-23",
    "racecourse_code": "07",
    "event_round": "04",
    "event_day": "01",
    "weekday_code": "1"
  },
  {
    "record_type_id": "YS",
    "data_division": "1",
    "data_created_date": "2024-12-20",
    "event_year": "2025",
    "event_date": "08-24",
    "racecourse_code": "01",
    "event_round": "02",
    "event_day": "02",
    "weekday_code": "2"
  },
  {
    "record_type_id": "YS",
    "data_division": "1",
    "data_created_date": "2024-12-20",
    "event_year": "2025",
    "event_date": "08-24",
    "racecourse_code": "04",
    "event_round": "03",
    "event_day": "02",
    "weekday_code": "2"
  },
  {
    "record_type_id": "YS",
    "data_division": "1",
    "data_created_date": "2024-12-20",
    "event_year": "2025",
    "event_date": "08-24",
    "racecourse_code": "07",
    "event_round": "04",
    "event_day": "02",
    "weekday_code": "2"
  },
  {
    "record_type_id": "YS",
    "data_division": "1",
    "data_created_date": "2024-12-20",
    "event_year": "2025",
    "event_date": "08-30",
    "racecourse_code": "01",
    "event_round": "02",
    "event_day": "03",
    "weekday_code": "1"
  },
  {
    "record_type_id": "YS",
    "data_division": "1",
    "data_created_date": "2024-12-20",
    "event_year": "2025",
    "event_date": "08-30",
    "racecourse_code": "04",
    "event_round": "03",
    "event_day": "03",
    "weekday_code": "1"
  },
  {
    "record_type_id": "YS",
    "data_division": "1",
    "data_created_date": "2024-12-20",
    "event_year": "2025",
    "event_date": "08-30",
    "racecourse_code": "07",
    "event_round": "04",
    "event_day": "03",
    "weekday_code": "1"
  },
  {
    "record_type_id": "YS",
    "data_division": "1",
    "data_created_date": "2024-12-20",
    "event_year": "2025",
    "event_date": "08-31",
    "racecourse_code": "01",
    "event_round": "02",
    "event_day": "04",
    "weekday_code": "2"
  },
  {
    "record_type_id": "YS",
    "data_division": "1",
    "data_created_date": "2024-12-20",
    "event_year": "2025",
    "event_date": "08-31",
    "racecourse_code": "04",
    "event_round": "03",
    "event_day": "04",
    "weekday_code": "2"
  },
  {
    "record_type_id": "YS",
    "data_division": "1",
    "data_created_date": "2024-12-20",
    "event_year": "2025",
    "event_date": "08-31",
    "racecourse_code": "07",
    "event_round": "04",
    "event_day": "04",
    "weekday_code": "2"
  },
  {
    "record_type_id": "YS",
    "data_division": "1",
    "data_created_date": "2024-12-20",
    "event_year": "2025",
    "event_date": "09-06",
    "racecourse_code": "01",
    "event_round": "02",
    "event_day": "05",
    "weekday_code": "1"
  },
  {
    "record_type_id": "YS",
    "data_division": "1",
    "data_created_date": "2024-12-20",
    "event_year": "2025",
    "event_date": "09-06",
    "racecourse_code": "06",
    "event_round": "04",
    "event_day": "01",
    "weekday_code": "1"
  },
  {
    "record_type_id": "YS",
    "data_division": "1",
    "data_created_date": "2024-12-20",
    "event_year": "2025",
    "event_date": "09-06",
    "racecourse_code": "09",
    "event_round": "04",
    "event_day": "01",
    "weekday_code": "1"
  },
  {
    "record_type_id": "YS",
    "data_division": "1",
    "data_created_date": "2024-12-20",
    "event_year": "2025",
    "event_date": "09-07",
    "racecourse_code": "01",
    "event_round": "02",
    "event_day": "06",
    "weekday_code": "2"
  },
  {
    "record_type_id": "YS",
    "data_division": "1",
    "data_created_date": "2024-12-20",
    "event_year": "2025",
    "event_date": "09-07",
    "racecourse_code": "06",
    "event_round": "04",
    "event_day": "02",
    "weekday_code": "2"
  },
  {
    "record_type_id": "YS",
    "data_division": "1",
    "data_created_date": "2024-12-20",
    "event_year": "2025",
    "event_date": "09-07",
    "racecourse_code": "09",
    "event_round": "04",
    "event_day": "02",
    "weekday_code": "2"
  },
  {
    "record_type_id": "YS",
    "data_division": "1",
    "data_created_date": "2024-12-20",
    "event_year": "2025",
    "event_date": "09-13",
    "racecourse_code": "06",
    "event_round": "04",
    "event_day": "03",
    "weekday_code": "1"
  },
  {
    "record_type_id": "YS",
    "data_division": "1",
    "data_created_date": "2024-12-20",
    "event_year": "2025",
    "event_date": "09-13",
    "racecourse_code": "09",
    "event_round": "04",
    "event_day": "03",
    "weekday_code": "1"
  },
  {
    "record_type_id": "YS",
    "data_division": "1",
    "data_created_date": "2024-12-20",
    "event_year": "2025",
    "event_date": "09-14",
    "racecourse_code": "06",
    "event_round": "04",
    "event_day": "04",
    "weekday_code": "2"
  },
  {
    "record_type_id": "YS",
    "data_division": "1",
    "data_created_date": "2024-12-20",
    "event_year": "2025",
    "event_date": "09-14",
    "racecourse_code": "09",
    "event_round": "04",
    "event_day": "04",
    "weekday_code": "2"
  },
  {
    "record_type_id": "YS",
    "data_division": "1",
    "data_created_date": "2024-12-20",
    "event_year": "2025",
    "event_date": "09-15",
    "racecourse_code": "06",
    "event_round": "04",
    "event_day": "05",
    "weekday_code": "3"
  },
  {
    "record_type_id": "YS",
    "data_division": "1",
    "data_created_date": "2024-12-20",
    "event_year": "2025",
    "event_date": "09-15",
    "racecourse_code": "09",
    "event_round": "04",
    "event_day": "05",
    "weekday_code": "3"
  },
  {
    "record_type_id": "YS",
    "data_division": "1",
    "data_created_date": "2024-12-20",
    "event_year": "2025",
    "event_date": "09-20",
    "racecourse_code": "06",
    "event_round": "04",
    "event_day": "06",
    "weekday_code": "1"
  },
  {
    "record_type_id": "YS",
    "data_division": "1",
    "data_created_date": "2024-12-20",
    "event_year": "2025",
    "event_date": "09-20",
    "racecourse_code": "09",
    "event_round": "04",
    "event_day": "06",
    "weekday_code": "1"
  },
  {
    "record_type_id": "YS",
    "data_division": "1",
    "data_created_date": "2024-12-20",
    "event_year": "2025",
    "event_date": "09-21",
    "racecourse_code": "06",
    "event_round": "04",
    "event_day": "07",
    "weekday_code": "2"
  },
  {
    "record_type_id": "YS",
    "data_division": "1",
    "data_created_date": "2024-12-20",
    "event_year": "2025",
    "event_date": "09-21",
    "racecourse_code": "09",
    "event_round": "04",
    "event_day": "07",
    "weekday_code": "2"
  },
  {
    "record_type_id": "YS",
    "data_division": "1",
    "data_created_date": "2024-12-20",
    "event_year": "2025",
    "event_date": "09-27",
    "racecourse_code": "06",
    "event_round": "04",
    "event_day": "08",
    "weekday_code": "1"
  },
  {
    "record_type_id": "YS",
    "data_division": "1",
    "data_created_date": "2024-12-20",
    "event_year": "2025",
    "event_date": "09-27",
    "racecourse_code": "09",
    "event_round": "04",
    "event_day": "08",
    "weekday_code": "1"
  },
  {
    "record_type_id": "YS",
    "data_division": "1",
    "data_created_date": "2024-12-20",
    "event_year": "2025",
    "event_date": "09-28",
    "racecourse_code": "06",
    "event_round": "04",
    "event_day": "09",
    "weekday_code": "2"
  },
  {
    "record_type_id": "YS",
    "data_division": "1",
    "data_created_date": "2024-12-20",
    "event_year": "2025",
    "event_date": "09-28",
    "racecourse_code": "09",
    "event_round": "04",
    "event_day": "09",
    "weekday_code": "2"
  },
  {
    "record_type_id": "YS",
    "data_division": "1",
    "data_created_date": "2024-12-20",
    "event_year": "2025",
    "event_date": "10-04",
    "racecourse_code": "05",
    "event_round": "04",
    "event_day": "01",
    "weekday_code": "1"
  },
  {
    "record_type_id": "YS",
    "data_division": "1",
    "data_created_date": "2024-12-20",
    "event_year": "2025",
    "event_date": "10-04",
    "racecourse_code": "08",
    "event_round": "03",
    "event_day": "01",
    "weekday_code": "1"
  },
  {
    "record_type_id": "YS",
    "data_division": "1",
    "data_created_date": "2024-12-20",
    "event_year": "2025",
    "event_date": "10-05",
    "racecourse_code": "05",
    "event_round": "04",
    "event_day": "02",
    "weekday_code": "2"
  },
  {
    "record_type_id": "YS",
    "data_division": "1",
    "data_created_date": "2024-12-20",
    "event_year": "2025",
    "event_date": "10-05",
    "racecourse_code": "08",
    "event_round": "03",
    "event_day": "02",
    "weekday_code": "2"
  },
  {
    "record_type_id": "YS",
    "data_division": "1",
    "data_created_date": "2024-12-20",
    "event_year": "2025",
    "event_date": "10-11",
    "racecourse_code": "05",
    "event_round": "04",
    "event_day": "03",
    "weekday_code": "1"
  },
  {
    "record_type_id": "YS",
    "data_division": "1",
    "data_created_date": "2024-12-20",
    "event_year": "2025",
    "event_date": "10-11",
    "racecourse_code": "08",
    "event_round": "03",
    "event_day": "03",
    "weekday_code": "1"
  },
  {
    "record_type_id": "YS",
    "data_division": "1",
    "data_created_date": "2024-12-20",
    "event_year": "2025",
    "event_date": "10-12",
    "racecourse_code": "05",
    "event_round": "04",
    "event_day": "04",
    "weekday_code": "2"
  },
  {
    "record_type_id": "YS",
    "data_division": "1",
    "data_created_date": "2024-12-20",
    "event_year": "2025",
    "event_date": "10-12",
    "racecourse_code": "08",
    "event_round": "03",
    "event_day": "04",
    "weekday_code": "2"
  },
  {
    "record_type_id": "YS",
    "data_division": "1",
    "data_created_date": "2024-12-20",
    "event_year": "2025",
    "event_date": "10-13",
    "racecourse_code": "05",
    "event_round": "04",
    "event_day": "05",
    "weekday_code": "3"
  },
  {
    "record_type_id": "YS",
    "data_division": "1",
    "data_created_date": "2024-12-20",
    "event_year": "2025",
    "event_date": "10-13",
    "racecourse_code": "08",
    "event_round": "03",
    "event_day": "05",
    "weekday_code": "3"
  },
  {
    "record_type_id": "YS",
    "data_division": "1",
    "data_created_date": "2024-12-20",
    "event_year": "2025",
    "event_date": "10-18",
    "racecourse_code": "04",
    "event_round": "04",
    "event_day": "01",
    "weekday_code": "1"
  },
  {
    "record_type_id": "YS",
    "data_division": "1",
    "data_created_date": "2024-12-20",
    "event_year": "2025",
    "event_date": "10-18",
    "racecourse_code": "05",
    "event_round": "04",
    "event_day": "06",
    "weekday_code": "1"
  },
  {
    "record_type_id": "YS",
    "data_division": "1",
    "data_created_date": "2024-12-20",
    "event_year": "2025",
    "event_date": "10-18",
    "racecourse_code": "08",
    "event_round": "03",
    "event_day": "06",
    "weekday_code": "1"
  },
  {
    "record_type_id": "YS",
    "data_division": "1",
    "data_created_date": "2024-12-20",
    "event_year": "2025",
    "event_date": "10-19",
    "racecourse_code": "04",
    "event_round": "04",
    "event_day": "02",
    "weekday_code": "2"
  },
  {
    "record_type_id": "YS",
    "data_division": "1",
    "data_created_date": "2024-12-20",
    "event_year": "2025",
    "event_date": "10-19",
    "racecourse_code": "05",
    "event_round": "04",
    "event_day": "07",
    "weekday_code": "2"
  },
  {
    "record_type_id": "YS",
    "data_division": "1",
    "data_created_date": "2024-12-20",
    "event_year": "2025",
    "event_date": "10-19",
    "racecourse_code": "08",
    "event_round": "03",
    "event_day": "07",
    "weekday_code": "2"
  },
  {
    "record_type_id": "YS",
    "data_division": "1",
    "data_created_date": "2024-12-20",
    "event_year": "2025",
    "event_date": "10-25",
    "racecourse_code": "04",
    "event_round": "04",
    "event_day": "03",
    "weekday_code": "1"
  },
  {
    "record_type_id": "YS",
    "data_division": "1",
    "data_created_date": "2024-12-20",
    "event_year": "2025",
    "event_date": "10-25",
    "racecourse_code": "05",
    "event_round": "04",
    "event_day": "08",
    "weekday_code": "1"
  },
  {
    "record_type_id": "YS",
    "data_division": "1",
    "data_created_date": "2024-12-20",
    "event_year": "2025",
    "event_date": "10-25",
    "racecourse_code": "08",
    "event_round": "03",
    "event_day": "08",
    "weekday_code": "1"
  },
  {
    "record_type_id": "YS",
    "data_division": "1",
    "data_created_date": "2024-12-20",
    "event_year": "2025",
    "event_date": "10-26",
    "racecourse_code": "04",
    "event_round": "04",
    "event_day": "04",
    "weekday_code": "2"
  },
  {
    "record_type_id": "YS",
    "data_division": "1",
    "data_created_date": "2024-12-20",
    "event_year": "2025",
    "event_date": "10-26",
    "racecourse_code": "05",
    "event_round": "04",
    "event_day": "09",
    "weekday_code": "2"
  },
  {
    "record_type_id": "YS",
    "data_division": "1",
    "data_created_date": "2024-12-20",
    "event_year": "2025",
    "event_date": "10-26",
    "racecourse_code": "08",
    "event_round": "03",
    "event_day": "09",
    "weekday_code": "2"
  },
  {
    "record_type_id": "YS",
    "data_division": "1",
    "data_created_date": "2024-12-20",
    "event_year": "2025",
    "event_date": "11-01",
    "racecourse_code": "05",
    "event_round": "04",
    "event_day": "10",
    "weekday_code": "1"
  },
  {
    "record_type_id": "YS",
    "data_division": "1",
    "data_created_date": "2024-12-20",
    "event_year": "2025",
    "event_date": "11-01",
    "racecourse_code": "08",
    "event_round": "03",
    "event_day": "10",
    "weekday_code": "1"
  },
  {
    "record_type_id": "YS",
    "data_division": "1",
    "data_created_date": "2024-12-20",
    "event_year": "2025",
    "event_date": "11-02",
    "racecourse_code": "05",
    "event_round": "04",
    "event_day": "11",
    "weekday_code": "2"
  },
  {
    "record_type_id": "YS",
    "data_division": "1",
    "data_created_date": "2024-12-20",
    "event_year": "2025",
    "event_date": "11-02",
    "racecourse_code": "08",
    "event_round": "03",
    "event_day": "11",
    "weekday_code": "2"
  },
  {
    "record_type_id": "YS",
    "data_division": "1",
    "data_created_date": "2024-12-20",
    "event_year": "2025",
    "event_date": "11-08",
    "racecourse_code": "03",
    "event_round": "03",
    "event_day": "01",
    "weekday_code": "1"
  },
  {
    "record_type_id": "YS",
    "data_division": "1",
    "data_created_date": "2024-12-20",
    "event_year": "2025",
    "event_date": "11-08",
    "racecourse_code": "05",
    "event_round": "05",
    "event_day": "01",
    "weekday_code": "1"
  },
  {
    "record_type_id": "YS",
    "data_division": "1",
    "data_created_date": "2024-12-20",
    "event_year": "2025",
    "event_date": "11-08",
    "racecourse_code": "08",
    "event_round": "04",
    "event_day": "01",
    "weekday_code": "1"
  },
  {
    "record_type_id": "YS",
    "data_division": "1",
    "data_created_date": "2024-12-20",
    "event_year": "2025",
    "event_date": "11-09",
    "racecourse_code": "03",
    "event_round": "03",
    "event_day": "02",
    "weekday_code": "2"
  },
  {
    "record_type_id": "YS",
    "data_division": "1",
    "data_created_date": "2024-12-20",
    "event_year": "2025",
    "event_date": "11-09",
    "racecourse_code": "05",
    "event_round": "05",
    "event_day": "02",
    "weekday_code": "2"
  },
  {
    "record_type_id": "YS",
    "data_division": "1",
    "data_created_date": "2024-12-20",
    "event_year": "2025",
    "event_date": "11-09",
    "racecourse_code": "08",
    "event_round": "04",
    "event_day": "02",
    "weekday_code": "2"
  },
  {
    "record_type_id": "YS",
    "data_division": "1",
    "data_created_date": "2024-12-20",
    "event_year": "2025",
    "event_date": "11-15",
    "racecourse_code": "03",
    "event_round": "03",
    "event_day": "03",
    "weekday_code": "1"
  },
  {
    "record_type_id": "YS",
    "data_division": "1",
    "data_created_date": "2024-12-20",
    "event_year": "2025",
    "event_date": "11-15",
    "racecourse_code": "05",
    "event_round": "05",
    "event_day": "03",
    "weekday_code": "1"
  },
  {
    "record_type_id": "YS",
    "data_division": "1",
    "data_created_date": "2024-12-20",
    "event_year": "2025",
    "event_date": "11-15",
    "racecourse_code": "08",
    "event_round": "04",
    "event_day": "03",
    "weekday_code": "1"
  },
  {
    "record_type_id": "YS",
    "data_division": "1",
    "data_created_date": "2024-12-20",
    "event_year": "2025",
    "event_date": "11-16",
    "racecourse_code": "03",
    "event_round": "03",
    "event_day": "04",
    "weekday_code": "2"
  },
  {
    "record_type_id": "YS",
    "data_division": "1",
    "data_created_date": "2024-12-20",
    "event_year": "2025",
    "event_date": "11-16",
    "racecourse_code": "05",
    "event_round": "05",
    "event_day": "04",
    "weekday_code": "2"
  },
  {
    "record_type_id": "YS",
    "data_division": "1",
    "data_created_date": "2024-12-20",
    "event_year": "2025",
    "event_date": "11-16",
    "racecourse_code": "08",
    "event_round": "04",
    "event_day": "04",
    "weekday_code": "2"
  },
  {
    "record_type_id": "YS",
    "data_division": "1",
    "data_created_date": "2024-12-20",
    "event_year": "2025",
    "event_date": "11-22",
    "racecourse_code": "03",
    "event_round": "03",
    "event_day": "05",
    "weekday_code": "1"
  },
  {
    "record_type_id": "YS",
    "data_division": "1",
    "data_created_date": "2024-12-20",
    "event_year": "2025",
    "event_date": "11-22",
    "racecourse_code": "08",
    "event_round": "04",
    "event_day": "05",
    "weekday_code": "1"
  },
  {
    "record_type_id": "YS",
    "data_division": "1",
    "data_created_date": "2024-12-20",
    "event_year": "2025",
    "event_date": "11-23",
    "racecourse_code": "05",
    "event_round": "05",
    "event_day": "05",
    "weekday_code": "3"
  },
  {
    "record_type_id": "YS",
    "data_division": "1",
    "data_created_date": "2024-12-20",
    "event_year": "2025",
    "event_date": "11-23",
    "racecourse_code": "08",
    "event_round": "04",
    "event_day": "06",
    "weekday_code": "3"
  },
  {
    "record_type_id": "YS",
    "data_division": "1",
    "data_created_date": "2024-12-20",
    "event_year": "2025",
    "event_date": "11-24",
    "racecourse_code": "03",
    "event_round": "03",
    "event_day": "06",
    "weekday_code": "4"
  },
  {
    "record_type_id": "YS",
    "data_division": "1",
    "data_created_date": "2024-12-20",
    "event_year": "2025",
    "event_date": "11-24",
    "racecourse_code": "05",
    "event_round": "05",
    "event_day": "06",
    "weekday_code": "4"
  },
  {
    "record_type_id": "YS",
    "data_division": "1",
    "data_created_date": "2024-12-20",
    "event_year": "2025",
    "event_date": "11-29",
    "racecourse_code": "05",
    "event_round": "05",
    "event_day": "07",
    "weekday_code": "1"
  },
  {
    "record_type_id": "YS",
    "data_division": "1",
    "data_created_date": "2024-12-20",
    "event_year": "2025",
    "event_date": "11-29",
    "racecourse_code": "08",
    "event_round": "04",
    "event_day": "07",
    "weekday_code": "1"
  },
  {
    "record_type_id": "YS",
    "data_division": "1",
    "data_created_date": "2024-12-20",
    "event_year": "2025",
    "event_date": "11-30",
    "racecourse_code": "05",
    "event_round": "05",
    "event_day": "08",
    "weekday_code": "2"
  },
  {
    "record_type_id": "YS",
    "data_division": "1",
    "data_created_date": "2024-12-20",
    "event_year": "2025",
    "event_date": "11-30",
    "racecourse_code": "08",
    "event_round": "04",
    "event_day": "08",
    "weekday_code": "2"
  },
  {
    "record_type_id": "YS",
    "data_division": "1",
    "data_created_date": "2024-12-20",
    "event_year": "2025",
    "event_date": "12-06",
    "racecourse_code": "06",
    "event_round": "05",
    "event_day": "01",
    "weekday_code": "1"
  },
  {
    "record_type_id": "YS",
    "data_division": "1",
    "data_created_date": "2024-12-20",
    "event_year": "2025",
    "event_date": "12-06",
    "racecourse_code": "07",
    "event_round": "05",
    "event_day": "01",
    "weekday_code": "1"
  },
  {
    "record_type_id": "YS",
    "data_division": "1",
    "data_created_date": "2024-12-20",
    "event_year": "2025",
    "event_date": "12-06",
    "racecourse_code": "09",
    "event_round": "05",
    "event_day": "01",
    "weekday_code": "1"
  },
  {
    "record_type_id": "YS",
    "data_division": "1",
    "data_created_date": "2024-12-20",
    "event_year": "2025",
    "event_date": "12-07",
    "racecourse_code": "06",
    "event_round": "05",
    "event_day": "02",
    "weekday_code": "2"
  },
  {
    "record_type_id": "YS",
    "data_division": "1",
    "data_created_date": "2024-12-20",
    "event_year": "2025",
    "event_date": "12-07",
    "racecourse_code": "07",
    "event_round": "05",
    "event_day": "02",
    "weekday_code": "2"
  },
  {
    "record_type_id": "YS",
    "data_division": "1",
    "data_created_date": "2024-12-20",
    "event_year": "2025",
    "event_date": "12-07",
    "racecourse_code": "09",
    "event_round": "05",
    "event_day": "02",
    "weekday_code": "2"
  },
  {
    "record_type_id": "YS",
    "data_division": "1",
    "data_created_date": "2024-12-20",
    "event_year": "2025",
    "event_date": "12-13",
    "racecourse_code": "06",
    "event_round": "05",
    "event_day": "03",
    "weekday_code": "1"
  },
  {
    "record_type_id": "YS",
    "data_division": "1",
    "data_created_date": "2024-12-20",
    "event_year": "2025",
    "event_date": "12-13",
    "racecourse_code": "07",
    "event_round": "05",
    "event_day": "03",
    "weekday_code": "1"
  },
  {
    "record_type_id": "YS",
    "data_division": "1",
    "data_created_date": "2024-12-20",
    "event_year": "2025",
    "event_date": "12-13",
    "racecourse_code": "09",
    "event_round": "05",
    "event_day": "03",
    "weekday_code": "1"
  },
  {
    "record_type_id": "YS",
    "data_division": "1",
    "data_created_date": "2024-12-20",
    "event_year": "2025",
    "event_date": "12-14",
    "racecourse_code": "06",
    "event_round": "05",
    "event_day": "04",
    "weekday_code": "2"
  },
  {
    "record_type_id": "YS",
    "data_division": "1",
    "data_created_date": "2024-12-20",
    "event_year": "2025",
    "event_date": "12-14",
    "racecourse_code": "07",
    "event_round": "05",
    "event_day": "04",
    "weekday_code": "2"
  },
  {
    "record_type_id": "YS",
    "data_division": "1",
    "data_created_date": "2024-12-20",
    "event_year": "2025",
    "event_date": "12-14",
    "racecourse_code": "09",
    "event_round": "05",
    "event_day": "04",
    "weekday_code": "2"
  },
  {
    "record_type_id": "YS",
    "data_division": "1",
    "data_created_date": "2024-12-20",
    "event_year": "2025",
    "event_date": "12-20",
    "racecourse_code": "06",
    "event_round": "05",
    "event_day": "05",
    "weekday_code": "1"
  },
  {
    "record_type_id": "YS",
    "data_division": "1",
    "data_created_date": "2024-12-20",
    "event_year": "2025",
    "event_date": "12-20",
    "racecourse_code": "07",
    "event_round": "05",
    "event_day": "05",
    "weekday_code": "1"
  },
  {
    "record_type_id": "YS",
    "data_division": "1",
    "data_created_date": "2024-12-20",
    "event_year": "2025",
    "event_date": "12-20",
    "racecourse_code": "09",
    "event_round": "05",
    "event_day": "05",
    "weekday_code": "1"
  },
  {
    "record_type_id": "YS",
    "data_division": "1",
    "data_created_date": "2024-12-20",
    "event_year": "2025",
    "event_date": "12-21",
    "racecourse_code": "06",
    "event_round": "05",
    "event_day": "06",
    "weekday_code": "2"
  },
  {
    "record_type_id": "YS",
    "data_division": "1",
    "data_created_date": "2024-12-20",
    "event_year": "2025",
    "event_date": "12-21",
    "racecourse_code": "07",
    "event_round": "05",
    "event_day": "06",
    "weekday_code": "2"
  },
  {
    "record_type_id": "YS",
    "data_division": "1",
    "data_created_date": "2024-12-20",
    "event_year": "2025",
    "event_date": "12-21",
    "racecourse_code": "09",
    "event_round": "05",
    "event_day": "06",
    "weekday_code": "2"
  },
  {
    "record_type_id": "YS",
    "data_division": "1",
    "data_created_date": "2024-12-20",
    "event_year": "2025",
    "event_date": "12-27",
    "racecourse_code": "06",
    "event_round": "05",
    "event_day": "07",
    "weekday_code": "1"
  },
  {
    "record_type_id": "YS",
    "data_division": "1",
    "data_created_date": "2024-12-20",
    "event_year": "2025",
    "event_date": "12-27",
    "racecourse_code": "09",
    "event_round": "05",
    "event_day": "07",
    "weekday_code": "1"
  },
  {
    "record_type_id": "YS",
    "data_division": "1",
    "data_created_date": "2024-12-20",
    "event_year": "2025",
    "event_date": "12-28",
    "racecourse_code": "06",
    "event_round": "05",
    "event_day": "08",
    "weekday_code": "2"
  },
  {
    "record_type_id": "YS",
    "data_division": "1",
    "data_created_date": "2024-12-20",
    "event_year": "2025",
    "event_date": "12-28",
    "racecourse_code": "09",
    "event_round": "05",
    "event_day": "08",
    "weekday_code": "2"
  }
]